setup.py
nijas_Gaussian_Binomial/Binomialdistribution.py
nijas_Gaussian_Binomial/Gaussiandistribution.py
nijas_Gaussian_Binomial/Generaldistribution.py
nijas_Gaussian_Binomial/__init__.py
nijas_Gaussian_Binomial.egg-info/PKG-INFO
nijas_Gaussian_Binomial.egg-info/SOURCES.txt
nijas_Gaussian_Binomial.egg-info/dependency_links.txt
nijas_Gaussian_Binomial.egg-info/not-zip-safe
nijas_Gaussian_Binomial.egg-info/top_level.txt