Metadata-Version: 1.0
Name: nijas-Gaussian-Binomial
Version: 0.1
Summary: Gaussian and Binomialdistributions
Home-page: UNKNOWN
Author: UNKNOWN
Author-email: UNKNOWN
License: UNKNOWN
Platform: UNKNOWN
